dbt/__init__.py
dbt/adapters/deltastream/__init__.py
dbt/adapters/deltastream/__version__.py
dbt/adapters/deltastream/column.py
dbt/adapters/deltastream/connections.py
dbt/adapters/deltastream/credentials.py
dbt/adapters/deltastream/impl.py
dbt/adapters/deltastream/relation.py
dbt/include/deltastream/__init__.py
dbt/include/deltastream/dbt_project.yml
dbt/include/deltastream/profile_template.yml
dbt/include/deltastream/sample_profiles.yml
dbt/include/deltastream/macros/adapters.sql
dbt/include/deltastream/macros/application.sql
dbt/include/deltastream/macros/catalog.sql
dbt/include/deltastream/macros/columns.sql
dbt/include/deltastream/macros/freshness.sql
dbt/include/deltastream/macros/relations.sql
dbt/include/deltastream/macros/restart.sql
dbt/include/deltastream/macros/terminate.sql
dbt/include/deltastream/macros/materializations/changelog.sql
dbt/include/deltastream/macros/materializations/compute_pool.sql
dbt/include/deltastream/macros/materializations/database.sql
dbt/include/deltastream/macros/materializations/descriptor_source.sql
dbt/include/deltastream/macros/materializations/entity.sql
dbt/include/deltastream/macros/materializations/function.sql
dbt/include/deltastream/macros/materializations/function_source.sql
dbt/include/deltastream/macros/materializations/incremental.sql
dbt/include/deltastream/macros/materializations/materialized_view.sql
dbt/include/deltastream/macros/materializations/schema_registry.sql
dbt/include/deltastream/macros/materializations/seeds.sql
dbt/include/deltastream/macros/materializations/source.sql
dbt/include/deltastream/macros/materializations/store.sql
dbt/include/deltastream/macros/materializations/stream.sql
dbt/include/deltastream/macros/materializations/table.sql
dbt/include/deltastream/macros/materializations/seeds/helpers.sql
dbt/include/deltastream/macros/tests/helpers.sql
dbt_deltastream-1.10.2.dist-info/METADATA
dbt_deltastream-1.10.2.dist-info/WHEEL
dbt_deltastream-1.10.2.dist-info/licenses/LICENSE
dbt_deltastream-1.10.2.dist-info/RECORD
