Metadata-Version: 2.4
Name: dbt-deltastream
Version: 1.10.2
Summary: The DeltaStream adapter plugin for dbt
Project-URL: Homepage, https://github.com/deltastreaminc/dbt-deltastream
Project-URL: Issues, https://github.com/deltastreaminc/dbt-deltastream/issues
Author-email: "DeltaStream Inc." <support@deltastream.com>
License-Expression: Apache-2.0
License-File: LICENSE
Classifier: Operating System :: MacOS :: MacOS X
Classifier: Operating System :: Microsoft :: Windows
Classifier: Operating System :: OS Independent
Classifier: Operating System :: POSIX :: Linux
Classifier: Programming Language :: Python :: 3
Classifier: Programming Language :: Python :: 3.11
Classifier: Programming Language :: Python :: 3.12
Classifier: Programming Language :: Python :: 3.13
Requires-Python: >=3.11
Requires-Dist: agate
Requires-Dist: dbt-adapters>=1.16
Requires-Dist: dbt-common<2.0,>=1.10
Requires-Dist: dbt-core>=1.10
Requires-Dist: deltastream-connector>=0.3
